napari_geojson/__init__.py
napari_geojson/_reader.py
napari_geojson/_version.py
napari_geojson/_writer.py
napari_geojson/napari.yaml
napari_geojson/_tests/__init__.py
napari_geojson/_tests/qp_all_shapes.geojson
napari_geojson/_tests/test_reader.py
napari_geojson/_tests/test_writer.py
napari_geojson-0.1.3.dist-info/LICENSE
napari_geojson-0.1.3.dist-info/METADATA
napari_geojson-0.1.3.dist-info/WHEEL
napari_geojson-0.1.3.dist-info/entry_points.txt
napari_geojson-0.1.3.dist-info/top_level.txt
napari_geojson-0.1.3.dist-info/RECORD
