Metadata-Version: 2.1
Name: napari-geojson
Version: 0.1.3
Summary: Read and write geojson files in napari
Home-page: https://github.com/tdmorello/napari-geojson
Author: Tim Morello
Author-email: tdmorello@gmail.com
License: BSD-3-Clause
Project-URL: Bug Tracker, https://github.com/tdmorello/napari-geojson/issues
Project-URL: Documentation, https://github.com/tdmorello/napari-geojson#README.md
Project-URL: Source Code, https://github.com/tdmorello/napari-geojson
Project-URL: User Support, https://github.com/tdmorello/napari-geojson/issues
Classifier: Development Status :: 3 - Alpha
Classifier: Framework :: napari
Classifier: Intended Audience :: Developers
Classifier: License :: OSI Approved :: BSD License
Classifier: Operating System :: OS Independent
Classifier: Programming Language :: Python
Classifier: Programming Language :: Python :: 3
Classifier: Programming Language :: Python :: 3 :: Only
Classifier: Programming Language :: Python :: 3.8
Classifier: Programming Language :: Python :: 3.9
Classifier: Programming Language :: Python :: 3.10
Classifier: Topic :: Scientific/Engineering :: Image Processing
Requires-Python: >=3.8
License-File: LICENSE
Requires-Dist: geojson
Requires-Dist: numpy
Provides-Extra: dev
Requires-Dist: black ; extra == 'dev'
Requires-Dist: flake8 ; extra == 'dev'
Requires-Dist: flake8-black ; extra == 'dev'
Requires-Dist: flake8-docstrings ; extra == 'dev'
Requires-Dist: flake8-isort ; extra == 'dev'
Requires-Dist: isort ; extra == 'dev'
Requires-Dist: mypy ; extra == 'dev'
Requires-Dist: pre-commit ; extra == 'dev'
Requires-Dist: pytest ; extra == 'dev'
Requires-Dist: pytest-cov ; extra == 'dev'
Requires-Dist: pytest-qt ; extra == 'dev'
Requires-Dist: tox ; extra == 'dev'
Provides-Extra: testing
Requires-Dist: napari[all] ; extra == 'testing'
Requires-Dist: pytest ; extra == 'testing'
Requires-Dist: pytest-cov ; extra == 'testing'
Requires-Dist: pytest-qt ; extra == 'testing'
Requires-Dist: tox ; extra == 'testing'
